{
	"slug": "kj-re",
	"released": 1712102400000,
	"duration": 266.419,
	"links": {
		"bandcamp": "https://erora.bandcamp.com/track/kj-re",
		"spotify": "https://open.spotify.com/track/3LW8WKMEsomrMefFC0P3ba",
		"appleMusic": "https://geo.music.apple.com/us/album/_/1739334400?i=1739334405&mt=1&app=music&ls=1&at=1000lHKX&ct=api_http&itscg=30200&itsct=odsl_m",
		"youtube": "https://www.youtube.com/watch?v=GJFnSs7cuWY",
		"songLink": "https://song.link/s/3LW8WKMEsomrMefFC0P3ba"
	},
	"label": "Kjøre",
	"description": [
		"Originally planned to be part of my next album, this track has a more organic feel. It was cut from the album due to its differences in sound, vibe, and mixing.",
		"",
		"Recorded during the Midten era. Produced on GarageBand for iOS."
	]
}
